optsmm/__init__.py
optsmm/optsmm.py
optsmm-1.0.1.dist-info/licenses/LICENSE
optsmm-1.0.1.dist-info/METADATA
optsmm-1.0.1.dist-info/WHEEL
optsmm-1.0.1.dist-info/top_level.txt
optsmm-1.0.1.dist-info/RECORD
