Metadata-Version: 2.4
Name: optsmm
Version: 1.0.1
Summary: Asynchronous package for using the optSMM API
Author-email: faidyy <faidyy@vk.com>
License: MIT
Classifier: Programming Language :: Python :: 3
Classifier: License :: OSI Approved :: MIT License
Classifier: Operating System :: OS Independent
Requires-Python: >=3.10
License-File: LICENSE
Dynamic: license-file
